scplotlib/__init__.py
scplotlib/scp_core.py
scplotlib/scp_heatmap.py
scplotlib/scp_outlierplots.py
scplotlib/scp_pcaplot.py
scplotlib/scp_silhouetteplot.py
scplotlib/scp_themes.py
scplotlib/scp_tsneplot.py
scplotlib-2.0.1.dist-info/LICENSE
scplotlib-2.0.1.dist-info/METADATA
scplotlib-2.0.1.dist-info/WHEEL
scplotlib-2.0.1.dist-info/top_level.txt
scplotlib-2.0.1.dist-info/RECORD
