Metadata-Version: 2.1
Name: scplotlib
Version: 2.0.1
Summary: A python package for visualizing the SingleCell data.
Home-page: https://edwinv87.github.io/scplotlib/
Author: Edwin Vans
Author-email: vans.edw@gmail.com
License: UNKNOWN
Platform: UNKNOWN
Classifier: Programming Language :: Python :: 3
Classifier: License :: OSI Approved :: MIT License
Classifier: Operating System :: OS Independent
Requires-Python: >=3.6
License-File: LICENSE
